{
  "_class": "symbolInstance",
  "booleanOperation": -1,
  "clippingMaskMode": 0,
  "do_objectID": "39BE0694-9F08-4961-9938-9E7A8D119BBA",
  "exportOptions": {
    "_class": "exportOptions",
    "do_objectID": "59AD552D-B457-4B4D-A84F-4885A1A3F987",
    "exportFormats": [
    ],
    "includedLayerIds": [
    ],
    "layerOptions": 0,
    "shouldTrim": false
  },
  "frame": {
    "_class": "rect",
    "constrainProportions": false,
    "do_objectID": "CD2BE185-CFC4-4BD7-97D2-1B8EEAF06EF3",
    "height": 20,
    "width": 40,
    "x": 130,
    "y": 0
  },
  "hasClippingMask": false,
  "horizontalSpacing": 0,
  "isFixedToViewport": false,
  "isFlippedHorizontal": false,
  "isFlippedVertical": false,
  "isLocked": false,
  "isVisible": true,
  "layerListExpandedType": 0,
  "name": "Atoms / Toggle / Off",
  "nameIsFixed": false,
  "overrideValues": [
  ],
  "resizingConstraint": 63,
  "resizingType": 0,
  "rotation": 0,
  "scale": 1,
  "shouldBreakMaskChain": false,
  "style": {
    "_class": "style",
    "do_objectID": "00C2B71E-13A8-4251-9521-7D14843FA227",
    "endMarkerType": 0,
    "miterLimit": 10,
    "startMarkerType": 0,
    "windingRule": 1
  },
  "symbolID": "4BD3D8E7-78B8-49F2-B478-77A242679E31",
  "verticalSpacing": 0
}