{
  "_class": "symbolInstance",
  "booleanOperation": -1,
  "clippingMaskMode": 0,
  "do_objectID": "82C27182-EBBC-46B1-A795-CA8F168CDF71",
  "exportOptions": {
    "_class": "exportOptions",
    "do_objectID": "5EE35406-61F8-419E-92C5-91D8EC86B7FF",
    "exportFormats": [
    ],
    "includedLayerIds": [
    ],
    "layerOptions": 0,
    "shouldTrim": false
  },
  "frame": {
    "_class": "rect",
    "constrainProportions": false,
    "do_objectID": "1FE530F9-FF79-4520-9843-5267CBBF702E",
    "height": 40,
    "width": 300,
    "x": 300,
    "y": 65
  },
  "hasClippingMask": false,
  "horizontalSpacing": 0,
  "isFixedToViewport": false,
  "isFlippedHorizontal": false,
  "isFlippedVertical": false,
  "isLocked": false,
  "isVisible": true,
  "layerListExpandedType": 0,
  "name": "Form elements / input text with embed icon / normal with placeholder",
  "nameIsFixed": false,
  "overrideValues": [
  ],
  "resizingConstraint": 63,
  "resizingType": 0,
  "rotation": 0,
  "scale": 1,
  "shouldBreakMaskChain": false,
  "style": {
    "_class": "style",
    "do_objectID": "7A9963EA-5D1A-4B81-85AA-EBFA70574385",
    "endMarkerType": 0,
    "miterLimit": 10,
    "startMarkerType": 0,
    "windingRule": 1
  },
  "symbolID": "72D73A8D-5DE5-443A-B0CE-76ED44DE002B",
  "verticalSpacing": 0
}