{
  "_class": "group",
  "booleanOperation": -1,
  "clippingMaskMode": 0,
  "do_objectID": "CAAD60EC-BB10-4F17-A092-6FE9D408A638",
  "exportOptions": {
    "_class": "exportOptions",
    "do_objectID": "0C1FF8B0-F26B-4341-8713-9C645935BB37",
    "exportFormats": [
    ],
    "includedLayerIds": [
    ],
    "layerOptions": 0,
    "shouldTrim": false
  },
  "frame": {
    "_class": "rect",
    "constrainProportions": false,
    "do_objectID": "D26E1BF3-D01C-4863-96E0-1528E39EF01E",
    "height": 16,
    "width": 16,
    "x": 0,
    "y": 0
  },
  "hasClickThrough": false,
  "hasClippingMask": false,
  "isFixedToViewport": false,
  "isFlippedHorizontal": false,
  "isFlippedVertical": false,
  "isLocked": false,
  "isVisible": true,
  "layerListExpandedType": 0,
  "layers": [
    {
      "class": "rectangle",
      "id": "4D423761-15CF-40FB-B006-ED9E9CF9394B"
    }
  ],
  "name": "colours/palettes/grey/#585858 - Grey",
  "nameIsFixed": false,
  "resizingConstraint": 63,
  "resizingType": 0,
  "rotation": 0,
  "shouldBreakMaskChain": false,
  "style": {
    "_class": "style",
    "do_objectID": "F73E4260-19F6-4392-A513-EBBB66ABFDD1",
    "endMarkerType": 0,
    "miterLimit": 10,
    "startMarkerType": 0,
    "windingRule": 1
  }
}