{
  "_class": "text",
  "attributedString": {
    "_class": "attributedString",
    "attributes": [
      {
        "_class": "stringAttribute",
        "attributes": {
          "MSAttributedStringColorAttribute": {
            "_class": "color",
            "alpha": 1,
            "blue": 0.2666666666666667,
            "green": 0.2666666666666667,
            "red": 0.2666666666666667
          },
          "MSAttributedStringFontAttribute": {
            "_class": "fontDescriptor",
            "attributes": {
              "name": "FiraSans-Light",
              "size": 32
            }
          },
          "kerning": -0.2000000029802322,
          "paragraphStyle": {
            "_class": "paragraphStyle",
            "maximumLineHeight": 44,
            "minimumLineHeight": 44
          }
        },
        "length": 8,
        "location": 0
      }
    ],
    "string": "Holdings"
  },
  "automaticallyDrawOnUnderlyingPath": false,
  "booleanOperation": -1,
  "clippingMaskMode": 0,
  "do_objectID": "AFAE38AD-609D-482C-B682-F810B67F02FE",
  "dontSynchroniseWithSymbol": false,
  "exportOptions": {
    "_class": "exportOptions",
    "do_objectID": "6D7AF45F-ADB6-41C6-94BD-FD7C7DAC0DA9",
    "exportFormats": [
    ],
    "includedLayerIds": [
    ],
    "layerOptions": 0,
    "shouldTrim": false
  },
  "frame": {
    "_class": "rect",
    "constrainProportions": false,
    "do_objectID": "DBFDE23C-A255-455B-86F2-474CD483E5C2",
    "height": 44,
    "width": 124,
    "x": 82,
    "y": 18
  },
  "glyphBounds": "{{3, 8}, {120, 32}}",
  "hasClippingMask": false,
  "isFixedToViewport": false,
  "isFlippedHorizontal": false,
  "isFlippedVertical": false,
  "isLocked": false,
  "isVisible": true,
  "layerListExpandedType": 0,
  "lineSpacingBehaviour": 2,
  "name": "Page heading",
  "nameIsFixed": true,
  "resizingConstraint": 47,
  "resizingType": 0,
  "rotation": 0,
  "sharedStyleID": "68BA8853-70AF-4AFF-8097-C959A02C5FD7",
  "shouldBreakMaskChain": false,
  "style": {
    "_class": "style",
    "do_objectID": "5375BF68-B11A-4EC4-93E4-7D0682644145",
    "endMarkerType": 0,
    "miterLimit": 10,
    "startMarkerType": 0,
    "textStyle": {
      "_class": "textStyle",
      "encodedAttributes": {
        "MSAttributedStringColorAttribute": {
          "_class": "color",
          "alpha": 1,
          "blue": 0.2666666666666667,
          "green": 0.2666666666666667,
          "red": 0.2666666666666667
        },
        "MSAttributedStringFontAttribute": {
          "_class": "fontDescriptor",
          "attributes": {
            "name": "FiraSans-Light",
            "size": 32
          }
        },
        "kerning": -0.2000000029802322,
        "paragraphStyle": {
          "_class": "paragraphStyle",
          "maximumLineHeight": 44,
          "minimumLineHeight": 44
        }
      },
      "verticalAlignment": 0
    },
    "windingRule": 1
  },
  "textBehaviour": 0
}