{
  "_class": "shapePath",
  "booleanOperation": -1,
  "clippingMaskMode": 0,
  "do_objectID": "B1B24B05-4E26-4BB6-B15F-83B769F0D0F8",
  "edited": true,
  "exportOptions": {
    "_class": "exportOptions",
    "do_objectID": "CB19FF5B-4B60-457C-B189-F220ECBEECF4",
    "exportFormats": [
    ],
    "includedLayerIds": [
    ],
    "layerOptions": 0,
    "shouldTrim": false
  },
  "frame": {
    "_class": "rect",
    "constrainProportions": false,
    "do_objectID": "ACF89E1F-EAA1-477D-8AD5-CCE5B7DDED3F",
    "height": 11,
    "width": 16,
    "x": 8,
    "y": 11
  },
  "hasClippingMask": false,
  "isClosed": true,
  "isFixedToViewport": false,
  "isFlippedHorizontal": false,
  "isFlippedVertical": false,
  "isLocked": false,
  "isVisible": true,
  "layerListExpandedType": 1,
  "name": "Shape",
  "nameIsFixed": false,
  "pointRadiusBehaviour": 1,
  "points": [
    {
      "_class": "curvePoint",
      "cornerRadius": 0,
      "curveFrom": "{0.89443049532070296, 0}",
      "curveMode": 1,
      "curveTo": "{0.89443049532070296, 0}",
      "hasCurveFrom": false,
      "hasCurveTo": false,
      "point": "{0.89443049532070296, 0}"
    },
    {
      "_class": "curvePoint",
      "cornerRadius": 0,
      "curveFrom": "{1, 0.14383333333333326}",
      "curveMode": 1,
      "curveTo": "{1, 0.14383333333333326}",
      "hasCurveFrom": false,
      "hasCurveTo": false,
      "point": "{1, 0.14383333333333326}"
    },
    {
      "_class": "curvePoint",
      "cornerRadius": 0,
      "curveFrom": "{0.429354028760557, 1}",
      "curveMode": 1,
      "curveTo": "{0.429354028760557, 1}",
      "hasCurveFrom": false,
      "hasCurveTo": false,
      "point": "{0.429354028760557, 1}"
    },
    {
      "_class": "curvePoint",
      "cornerRadius": 0,
      "curveFrom": "{0, 0.38550000000000012}",
      "curveMode": 1,
      "curveTo": "{0, 0.38550000000000012}",
      "hasCurveFrom": false,
      "hasCurveTo": false,
      "point": "{0, 0.38550000000000012}"
    },
    {
      "_class": "curvePoint",
      "cornerRadius": 0,
      "curveFrom": "{0.10591189226204072, 0.22950000000000012}",
      "curveMode": 1,
      "curveTo": "{0.10591189226204072, 0.22950000000000012}",
      "hasCurveFrom": false,
      "hasCurveTo": false,
      "point": "{0.10591189226204072, 0.22950000000000012}"
    },
    {
      "_class": "curvePoint",
      "cornerRadius": 0,
      "curveFrom": "{0.429354028760557, 0.70833333333333337}",
      "curveMode": 1,
      "curveTo": "{0.429354028760557, 0.70833333333333337}",
      "hasCurveFrom": false,
      "hasCurveTo": false,
      "point": "{0.429354028760557, 0.70833333333333337}"
    }
  ],
  "resizingConstraint": 63,
  "resizingType": 0,
  "rotation": 0,
  "shouldBreakMaskChain": false,
  "style": {
    "_class": "style",
    "do_objectID": "353A5712-AB78-4762-8526-71904BF486B4",
    "endMarkerType": 0,
    "fills": [
      {
        "_class": "fill",
        "color": {
          "_class": "color",
          "alpha": 1,
          "blue": 0.2902374565601349,
          "green": 0.2901752889156342,
          "red": 0.290221631526947
        },
        "fillType": 0,
        "isEnabled": true,
        "noiseIndex": 0,
        "noiseIntensity": 0,
        "patternFillType": 1,
        "patternTileScale": 1
      }
    ],
    "miterLimit": 10,
    "startMarkerType": 0,
    "windingRule": 1
  }
}