{
  "_class": "shapeGroup",
  "booleanOperation": 0,
  "clippingMaskMode": 0,
  "do_objectID": "76D31FEB-8266-42D4-B67D-00E6E7ECD8E0",
  "exportOptions": {
    "_class": "exportOptions",
    "do_objectID": "0506CFFE-1507-4D63-8EF4-77781BAB0B80",
    "exportFormats": [
    ],
    "includedLayerIds": [
    ],
    "layerOptions": 0,
    "shouldTrim": false
  },
  "frame": {
    "_class": "rect",
    "constrainProportions": false,
    "do_objectID": "D3FC7D81-96CF-464D-ADBB-52E23622A24E",
    "height": 32,
    "width": 32,
    "x": 0,
    "y": 0
  },
  "hasClickThrough": false,
  "hasClippingMask": false,
  "isFixedToViewport": false,
  "isFlippedHorizontal": false,
  "isFlippedVertical": false,
  "isLocked": false,
  "isVisible": true,
  "layerListExpandedType": 0,
  "layers": [
    {
      "class": "shapePath",
      "id": "19661D2C-ED39-45CD-92B2-3BE37F432622"
    },
    {
      "class": "shapePath",
      "id": "087A7155-572A-4AF4-AEA5-5E1A9AFA718C"
    }
  ],
  "name": "Shape",
  "nameIsFixed": false,
  "resizingConstraint": 63,
  "resizingType": 0,
  "rotation": 0,
  "shouldBreakMaskChain": false,
  "style": {
    "_class": "style",
    "do_objectID": "6BB27F61-1492-4724-9E11-9B68B816416F",
    "endMarkerType": 0,
    "fills": [
      {
        "_class": "fill",
        "color": {
          "_class": "color",
          "alpha": 1,
          "blue": 0.2902374565601349,
          "green": 0.2901752889156342,
          "red": 0.290221631526947
        },
        "fillType": 0,
        "isEnabled": true,
        "noiseIndex": 0,
        "noiseIntensity": 0,
        "patternFillType": 1,
        "patternTileScale": 1
      }
    ],
    "miterLimit": 10,
    "startMarkerType": 0,
    "windingRule": 1
  },
  "windingRule": 1
}