{
  "_class": "bitmap",
  "booleanOperation": -1,
  "clippingMask": "{{0, 0}, {1, 1}}",
  "clippingMaskMode": 0,
  "do_objectID": "7CD275B6-9BF5-46C1-BAD0-4B36C91F9EFB",
  "exportOptions": {
    "_class": "exportOptions",
    "do_objectID": "248E438B-4820-427A-9B2C-D5A0A938433A",
    "exportFormats": [
    ],
    "includedLayerIds": [
    ],
    "layerOptions": 0,
    "shouldTrim": false
  },
  "fillReplacesImage": false,
  "frame": {
    "_class": "rect",
    "constrainProportions": true,
    "do_objectID": "8F2D4901-C591-42DD-A05F-B91A9639DAA4",
    "height": 421,
    "width": 392,
    "x": 533,
    "y": 1010
  },
  "hasClippingMask": false,
  "image": {
    "_class": "MSJSONFileReference",
    "_ref": "images/f0f1945e2c4014a9e9fa93154dd568b13de621b3.png",
    "_ref_class": "MSImageData"
  },
  "intendedDPI": 72,
  "isFixedToViewport": false,
  "isFlippedHorizontal": false,
  "isFlippedVertical": false,
  "isLocked": false,
  "isVisible": true,
  "layerListExpandedType": 0,
  "name": "Screenshot 2019-02-11 at 10.39.46",
  "nameIsFixed": false,
  "resizingConstraint": 63,
  "resizingType": 0,
  "rotation": 0,
  "shouldBreakMaskChain": false,
  "style": {
    "_class": "style",
    "do_objectID": "5312E837-3BF5-4309-B798-9862C9F1C7E3",
    "endMarkerType": 0,
    "miterLimit": 10,
    "startMarkerType": 0,
    "windingRule": 1
  }
}